chromosomes/__init__.py
chromosomes/apps.py
chromosomes/models.py
chromosomes/settings.py
chromosomes/urls.py
chromosomes/views.py
chromosomes/wsgi.py
dna/__init__.py
dna/apps.py
dna/crispr.py
dna/dna.py
dna/forms.py
dna/models.py
dna/replicate.py
dna/settings.py
dna/view_mixins.py
dna/view_utils.py
dna/views.py
dna/watermark.py
dna/management/commands/__init__.py
dna/management/commands/dna.py
dna/management/commands/genome.py
dna/templates/dna/_menu.html
dna/templates/dna/_page_engaged.html
dna/templates/dna/_page_listed.html
dna/templates/dna/_page_listed_paginator.html
dna/templates/dna/_thing_confirm_delete.html
dna/templates/dna/_thing_engaged.html
dna/templates/dna/_thing_field.html
dna/templates/dna/_thing_form.html
dna/templates/dna/_thing_listed.html
dna/templates/dna/_thing_many.html
dna/templates/dna/_thing_paginator.html
dna/templatetags/__init__.py
dna/templatetags/dna_tags.py
elio_dna-1.0.7.dist-info/LICENSE
elio_dna-1.0.7.dist-info/METADATA
elio_dna-1.0.7.dist-info/WHEEL
elio_dna-1.0.7.dist-info/top_level.txt
elio_dna-1.0.7.dist-info/RECORD
