Metadata-Version: 2.1
Name: elio-dna
Version: 1.0.7
Summary: Django models, views, forms, and templates, built on schema.org Things the elioWay.
Home-page: https://elioway.gitlab.io/eliothing/dna
Author: Tim Bushell
Author-email: tcbushell@gmail.com
License: MIT
Platform: UNKNOWN
Classifier: Development Status :: 1 - Planning
Classifier: Environment :: Console
Classifier: Framework :: Django :: 2.2
Classifier: Intended Audience :: Developers
Classifier: License :: OSI Approved :: MIT License
Classifier: Natural Language :: English
Classifier: Operating System :: OS Independent
Classifier: Programming Language :: Python
Classifier: Programming Language :: Python :: 3
Classifier: Topic :: Software Development :: Libraries
Classifier: Topic :: Internet :: WWW/HTTP :: Dynamic Content :: Content Management System
Requires-Dist: elio-apep
Requires-Dist: Django
Requires-Dist: django-polymorphic
Requires-Dist: easy-thumbnails
Requires-Dist: Pillow
Requires-Dist: python-slugify
